procurement_tools/__init__.py
procurement_tools/cli/__init__.py
procurement_tools/cli/main.py
procurement_tools/data/periodic_table.json
procurement_tools/far.py
procurement_tools/models/__init__.py
procurement_tools/models/entity.py
procurement_tools/models/far_clause.py
procurement_tools/models/opportunities.py
procurement_tools/models/sam_entity/far_answer.py
procurement_tools/models/sbir.py
procurement_tools/periodic_table.py
procurement_tools/sam.py
procurement_tools/sbir.py
procurement_tools/uei.py
procurement_tools/usaspending.py
procurement_tools-0.2.2.dist-info/LICENSE.md
procurement_tools-0.2.2.dist-info/METADATA
procurement_tools-0.2.2.dist-info/WHEEL
procurement_tools-0.2.2.dist-info/entry_points.txt
procurement_tools-0.2.2.dist-info/RECORD
