Metadata-Version: 2.1
Name: procurement-tools
Version: 0.2.2
Summary: Python tools for navigating federal contracting
Home-page: https://pypi.org/project/procurement-tools/
License: Apache-2.0
Keywords: packaging,poetry
Author: V. David Zvenyach
Author-email: dave@tandemgov.com
Requires-Python: >=3.8,<4.0
Classifier: License :: OSI Approved :: Apache Software License
Classifier: Programming Language :: Python :: 3
Classifier: Programming Language :: Python :: 3.8
Classifier: Programming Language :: Python :: 3.9
Classifier: Programming Language :: Python :: 3.10
Classifier: Programming Language :: Python :: 3.11
Classifier: Programming Language :: Python :: 3.12
Requires-Dist: beautifulsoup4 (>=4.12.2,<5.0.0)
Requires-Dist: cssselect (>=1.2.0,<2.0.0)
Requires-Dist: httpx (>=0.25.2,<0.26.0)
Requires-Dist: keyring (>=24.3.0,<25.0.0)
Requires-Dist: pydantic (>=2.5.1,<3.0.0)
Requires-Dist: requests (>=2.31.0,<3.0.0)
Requires-Dist: rich (>=13.7.0,<14.0.0)
Requires-Dist: typer (>=0.9.0,<0.10.0)
Project-URL: Documentation, https://procurement-tools.readthedocs.io/en/latest/
Project-URL: Repository, https://github.com/tandemgov/procurement-tools
